.coveragerc
.coveralls.yaml
.readthedocs.yaml
CHANGES.rst
COPYRIGHT.rst
LICENSE.rst
MANIFEST.in
Makefile
README.rst
constraints.txt
setup.py
sphinx/conf.py
src/manuel/README.txt
src/manuel/__init__.py
src/manuel/bugs.txt
src/manuel/capture.py
src/manuel/capture.txt
src/manuel/codeblock.py
src/manuel/doc1.ex
src/manuel/doc2.ex
src/manuel/doc3.ex
src/manuel/doctest.py
src/manuel/footnote.py
src/manuel/ignore.py
src/manuel/index.txt
src/manuel/isolation.py
src/manuel/myst-markdown.md
src/manuel/table-example.txt
src/manuel/testcase.py
src/manuel/testing.py
src/manuel/tests.py
src/manuel.egg-info/PKG-INFO
src/manuel.egg-info/SOURCES.txt
src/manuel.egg-info/dependency_links.txt
src/manuel.egg-info/not-zip-safe
src/manuel.egg-info/requires.txt
src/manuel.egg-info/top_level.txt
src/manuel/myst/__init__.py
src/manuel/myst/codeblock.py