Metadata-Version: 2.1
Name: manuel
Version: 1.13.0
Summary: Manuel lets you build tested documentation.
Home-page: http://pypi.python.org/pypi/manuel
Author: Benji York
Author-email: benji@benjiyork.com
License: Apache Software License, Version 2.0
Keywords: testing,documentation
Classifier: Programming Language :: Python :: 3
Classifier: Programming Language :: Python :: 3.7
Classifier: Programming Language :: Python :: 3.8
Classifier: Programming Language :: Python :: 3.9
Classifier: Programming Language :: Python :: 3.10
Classifier: Programming Language :: Python :: Implementation :: CPython
Classifier: Programming Language :: Python :: Implementation :: PyPy
Classifier: License :: OSI Approved :: Apache Software License
License-File: LICENSE.rst
Requires-Dist: setuptools
Provides-Extra: tests
Requires-Dist: zope.testing; extra == "tests"
